{
  "$schema": "https://raw.githubusercontent.com/streetsidesoftware/cspell/main/cspell.schema.json",
  "version": "0.2",
  "language": "en",
  "words": [
    "ako",
    "bio",
    "biti",
    "browsera",
    "čak",
    "će",
    "čuvamo",
    "da",
    "garantuje",
    "ista",
    "izazove",
    "je",
    "jednom",
    "jer",
    "koji",
    "komponenta",
    "komponentu",
    "kopiramo",
    "lokalnu",
    "međuvremenu",
    "montirana",
    "na",
    "naslov",
    "ne",
    "nego",
    "nema",
    "odgovornost",
    "originalni",
    "ova",
    "ovu",
    "pamtimo",
    "pokreće",
    "praznim",
    "preuzima",
    "promeni",
    "renderuje",
    "sa",
    "samo",
    "se",
    "serveru",
    "spreman",
    "stiže",
    "što",
    "u",
    "varijablu",
    "već",
    "vrednost",
    "za",
    "želimo"
  ],
  "ignorePaths": [
    "node_modules/**",
    ".next/**",
    "*.lock"
  ]
}
